{
  "label": "legacy_jsonl",
  "trade_count": 34,
  "winner_count": 21,
  "loser_count": 13,
  "breakeven_count": 0,
  "win_rate": 0.6176,
  "total_pnl": 7142.6,
  "avg_pnl": 210.08,
  "median_pnl": 169.1,
  "session_day": 14,
  "session_night": 20,
  "exit_reason_counts": {},
  "final_exit_reason_counts": {},
  "trade_ids": [
    "mts-20260709-085624",
    "mts-20260709-125527",
    "mts-20260709-170042",
    "mts-20260713-085856",
    "mts-20260713-150331",
    "mts-20260713-175629",
    "mts-20260714-203416",
    "mts-20260716-131700",
    "mts-auto-001713-248",
    "mts-auto-005252-372",
    "mts-auto-085335-236",
    "mts-auto-085837-764",
    "mts-auto-090244-130",
    "mts-auto-094447-171",
    "mts-auto-095417-769",
    "mts-auto-101709-433",
    "mts-auto-105607-780",
    "mts-auto-114904-854",
    "mts-auto-131539-634",
    "mts-auto-133741-001",
    "mts-auto-150001-119",
    "mts-auto-152003-393",
    "mts-auto-160857-726",
    "mts-auto-161229-714",
    "mts-auto-165644-850",
    "mts-auto-183042-480",
    "mts-auto-183154-722",
    "mts-auto-202908-887",
    "mts-auto-212849-633",
    "mts-auto-213700-512",
    "mts-auto-214943-083",
    "mts-auto-215657-960",
    "mts-auto-221230-855",
    "mts-auto-224409-884"
  ]
}